nessusha/__init__.py
nessusha/testing.py
nessusha/v3.py
nessusha-0.3.0.dist-info/METADATA
nessusha-0.3.0.dist-info/RECORD
nessusha-0.3.0.dist-info/WHEEL
nessusha-0.3.0.dist-info/top_level.txt
