Metadata-Version: 2.1
Name: nessusha
Version: 0.3.0
Summary: Extract Nessus HA data to xlsx
Home-page: https://github.com/SanPersie
Author: Li Xingxuan
Author-email: lxx895466249@gmail.com
License: UNKNOWN
Platform: UNKNOWN
Classifier: Programming Language :: Python :: 3
Classifier: License :: OSI Approved :: MIT License
Classifier: Operating System :: OS Independent
Requires-Dist: bs4
Requires-Dist: xlsxwriter
